<!DOCTYPE controller>
<controller>
  <controls>
    <control>
      <group>[Master]</group>
      <key>crossfader</key>
      <miditype>Ctrl</miditype>
      <midinum>17</midinum>
      <midichan>1</midichan>
    </control>
    <control>
      <group>[Master]</group>
      <key>balance</key>
      <miditype>Ctrl</miditype>
      <midinum>32</midinum>
      <midichan>1</midichan>
    </control>
    <control>
      <group>[Master]</group>
      <key>volume</key>
      <miditype>Ctrl</miditype>
      <midinum>33</midinum>
      <midichan>1</midichan>
    </control>
    <control>
      <group>[Master]</group>
      <key>headVolume</key>
      <miditype>Ctrl</miditype>
      <midinum>26</midinum>
      <midichan>1</midichan>
    </control>
    <control>
      <group>[Master]</group>
      <key>headMix</key>
      <miditype>Ctrl</miditype>
      <midinum>25</midinum>
      <midichan>1</midichan>
    </control>
    <control>
      <group>[Channel1]</group>
      <key>play</key>
      <miditype>Key</miditype>
      <midinum>70</midinum>
      <midichan>1</midichan>
    </control>
    <control>
      <group>[Channel1]</group>
      <key>reverse</key>
      <miditype>Key</miditype>
      <midinum>46</midinum>
      <midichan>1</midichan>
    </control>
    <control>
      <group>[Channel1]</group>
      <key>fwd</key>
      <miditype>Key</miditype>
      <midinum>43</midinum>
      <midichan>1</midichan>
    </control>
    <control>
      <group>[Channel1]</group>
      <key>volume</key>
      <miditype>Ctrl</miditype>
      <midinum>11</midinum>
      <midichan>1</midichan>
    </control>
    <control>
      <group>[Channel1]</group>
      <key>rate</key>
      <miditype>Ctrl</miditype>
      <midinum>12</midinum>
      <midichan>1</midichan>
    </control>
    <control>
      <group>[Channel1]</group>
      <key>pfl</key>
      <miditype>Key</miditype>
      <midinum>44</midinum>
      <midichan>1</midichan>
    </control>
    <control>
      <group>[Channel1]</group>
      <key>cue_simple</key>
      <miditype>Key</miditype>
      <midinum>58</midinum>
      <midichan>1</midichan>
    </control>
    <control>
      <group>[Channel1]</group>
      <key>filterLow</key>
      <miditype>Ctrl</miditype>
      <midinum>29</midinum>
      <midichan>1</midichan>
    </control>
    <control>
      <group>[Channel1]</group>
      <key>filterMid</key>
      <miditype>Ctrl</miditype>
      <midinum>28</midinum>
      <midichan>1</midichan>
    </control>
    <control>
      <group>[Channel1]</group>
      <key>filterHigh</key>
      <miditype>Ctrl</miditype>
      <midinum>27</midinum>
      <midichan>1</midichan>
    </control>
    <control>
      <group>[Channel1]</group>
      <key>pregain</key>
      <miditype>Ctrl</miditype>
      <midinum>24</midinum>
      <midichan>1</midichan>
    </control>
    <control>
      <group>[Channel2]</group>
      <key>play</key>
      <miditype>Key</miditype>
      <midinum>69</midinum>
      <midichan>1</midichan>
    </control>
    <control>
      <group>[Channel2]</group>
      <key>reverse</key>
      <miditype>Key</miditype>
      <midinum>56</midinum>
      <midichan>1</midichan>
    </control>
    <control>
      <group>[Channel2]</group>
      <key>fwd</key>
      <miditype>Key</miditype>
      <midinum>57</midinum>
      <midichan>1</midichan>
    </control>
    <control>
      <group>[Channel2]</group>
      <key>volume</key>
      <miditype>Ctrl</miditype>
      <midinum>14</midinum>
      <midichan>1</midichan>
    </control>
    <control>
      <group>[Channel2]</group>
      <key>rate</key>
      <miditype>Ctrl</miditype>
      <midinum>15</midinum>
      <midichan>1</midichan>
    </control>
    <control>
      <group>[Channel2]</group>
      <key>pfl</key>
      <miditype>Key</miditype>
      <midinum>45</midinum>
      <midichan>1</midichan>
    </control>
    <control>
      <group>[Channel2]</group>
      <key>cue_simple</key>
      <miditype>Key</miditype>
      <midinum>59</midinum>
      <midichan>1</midichan>
    </control>
    <control>
      <group>[Channel2]</group>
      <key>filterLow</key>
      <miditype>Ctrl</miditype>
      <midinum>36</midinum>
      <midichan>1</midichan>
    </control>
    <control>
      <group>[Channel2]</group>
      <key>filterMid</key>
      <miditype>Ctrl</miditype>
      <midinum>35</midinum>
      <midichan>1</midichan>
    </control>
    <control>
      <group>[Channel2]</group>
      <key>filterHigh</key>
      <miditype>Ctrl</miditype>
      <midinum>34</midinum>
      <midichan>1</midichan>
    </control>
    <control>
      <group>[Channel2]</group>
      <key>pregain</key>
      <miditype>Ctrl</miditype>
      <midinum>31</midinum>
      <midichan>1</midichan>
    </control>
  </controls>
</controller>
