<!DOCTYPE controller>
<controller>
  <controls>
    <control>
      <group>[Master]</group>
      <key>crossfader</key>
      <miditype>Ctrl</miditype>
      <midinum>1</midinum>
      <midichan>1</midichan>
    </control>
    <control>
      <group>[Channel1]</group>
      <key>play</key>
      <miditype>Key</miditype>
      <midinum>36</midinum>
      <midichan>1</midichan>
    </control>
    <control>
      <group>[Channel1]</group>
      <key>reverse</key>
      <miditype>Key</miditype>
      <midinum>38</midinum>
      <midichan>1</midichan>
    </control>
    <control>
      <group>[Channel1]</group>
      <key>back</key>
      <miditype>Key</miditype>
      <midinum>40</midinum>
      <midichan>1</midichan>
    </control>
    <control>
      <group>[Channel1]</group>
      <key>fwd</key>
      <miditype>Key</miditype>
      <midinum>41</midinum>
      <midichan>1</midichan>
    </control>
    <control>
      <group>[Channel1]</group>
      <key>rate_perm_down</key>
      <miditype>Key</miditype>
      <midinum>43</midinum>
      <midichan>1</midichan>
    </control>
    <control>
      <group>[Channel1]</group>
      <key>rate_perm_up</key>
      <miditype>Key</miditype>
      <midinum>44</midinum>
      <midichan>1</midichan>
    </control>
    <control>
      <group>[Channel1]</group>
      <key>rate_temp_down</key>
      <miditype>Key</miditype>
      <midinum>45</midinum>
      <midichan>1</midichan>
    </control>
    <control>
      <group>[Channel1]</group>
      <key>rate_temp_up</key>
      <miditype>Key</miditype>
      <midinum>46</midinum>
      <midichan>1</midichan>
    </control>
    <control>
      <group>[Channel1]</group>
      <key>cue_simple</key>
      <miditype>Key</miditype>
      <midinum>47</midinum>
      <midichan>1</midichan>
    </control>
    <control>
      <group>[Channel1]</group>
      <key>flanger</key>
      <miditype>Key</miditype>
      <midinum>52</midinum>
      <midichan>1</midichan>
    </control>
    <control>
      <group>[Channel2]</group>
      <key>play</key>
      <miditype>Key</miditype>
      <midinum>60</midinum>
      <midichan>1</midichan>
    </control>
    <control>
      <group>[Channel2]</group>
      <key>reverse</key>
      <miditype>Key</miditype>
      <midinum>62</midinum>
      <midichan>1</midichan>
    </control>
    <control>
      <group>[Channel2]</group>
      <key>back</key>
      <miditype>Key</miditype>
      <midinum>64</midinum>
      <midichan>1</midichan>
    </control>
    <control>
      <group>[Channel2]</group>
      <key>fwd</key>
      <miditype>Key</miditype>
      <midinum>65</midinum>
      <midichan>1</midichan>
    </control>
    <control>
      <group>[Channel2]</group>
      <key>rate_perm_down</key>
      <miditype>Key</miditype>
      <midinum>67</midinum>
      <midichan>1</midichan>
    </control>
    <control>
      <group>[Channel2]</group>
      <key>rate_perm_up</key>
      <miditype>Key</miditype>
      <midinum>68</midinum>
      <midichan>1</midichan>
    </control>
    <control>
      <group>[Channel2]</group>
      <key>rate_temp_down</key>
      <miditype>Key</miditype>
      <midinum>69</midinum>
      <midichan>1</midichan>
    </control>
    <control>
      <group>[Channel2]</group>
      <key>rate_temp_up</key>
      <miditype>Key</miditype>
      <midinum>70</midinum>
      <midichan>1</midichan>
    </control>
    <control>
      <group>[Channel2]</group>
      <key>cue_simple</key>
      <miditype>Key</miditype>
      <midinum>71</midinum>
      <midichan>1</midichan>
    </control>
    <control>
      <group>[Channel2]</group>
      <key>flanger</key>
      <miditype>Key</miditype>
      <midinum>76</midinum>
      <midichan>1</midichan>
    </control>
  </controls>
</controller>
